wraplot/__init__.py
wraplot/plotter.py
wraplot/plotter_definitions.py
wraplot-0.1.1.dist-info/LICENSE
wraplot-0.1.1.dist-info/WHEEL
wraplot-0.1.1.dist-info/METADATA
wraplot-0.1.1.dist-info/RECORD
