Metadata-Version: 2.1
Name: wraplot
Version: 0.1.1
Summary: A simple python wrapper of matplotlib
Home-page: https://github.com/LucaMoschella/wraplot
License: MIT
Author: Luca Moschella
Author-email: luca.moschella94@gmail.com
Requires-Python: >=3.7,<4.0
Classifier: License :: OSI Approved :: MIT License
Classifier: Programming Language :: Python :: 3
Classifier: Programming Language :: Python :: 3.7
Classifier: Programming Language :: Python :: 3.8
Requires-Dist: imageio (>=2.6.1,<3.0.0)
Requires-Dist: imageio-ffmpeg (>=0.3.0,<0.4.0)
Requires-Dist: matplotlib (>=3.1.2,<4.0.0)
Requires-Dist: numpy (>=1.17.4,<2.0.0)
Requires-Dist: streamlit (>=0.51.0,<0.52.0)
Project-URL: Repository, https://github.com/LucaMoschella/wraplot
